alumath_peergroup_6/__init__.py
alumath_peergroup_6/exceptions.py
alumath_peergroup_6/matrix.py
alumath_peergroup_6/operations.py
alumath_peergroup_6-1.0.0.dist-info/LICENSE
alumath_peergroup_6-1.0.0.dist-info/METADATA
alumath_peergroup_6-1.0.0.dist-info/WHEEL
alumath_peergroup_6-1.0.0.dist-info/top_level.txt
alumath_peergroup_6-1.0.0.dist-info/RECORD
