Metadata-Version: 2.1
Name: alumath-peergroup-6
Version: 1.0.0
Summary: A Python library for matrix multiplication with support for different dimensions
Home-page: https://github.com/peergroup6/alumath_peergroup_6
Author: Peergroup 6
Author-email: peergroup6@example.com
License: MIT
Project-URL: Bug Reports, https://github.com/peergroup6/alumath_peergroup_6/issues
Project-URL: Source, https://github.com/peergroup6/alumath_peergroup_6
Project-URL: Documentation, https://github.com/peergroup6/alumath_peergroup_6/wiki
Keywords: matrix multiplication linear algebra mathematics
Platform: UNKNOWN
Classifier: Development Status :: 4 - Beta
Classifier: Intended Audience :: Developers
Classifier: Intended Audience :: Science/Research
Classifier: License :: OSI Approved :: MIT License
Classifier: Operating System :: OS Independent
Classifier: Programming Language :: Python :: 3
Classifier: Programming Language :: Python :: 3.7
Classifier: Programming Language :: Python :: 3.8
Classifier: Programming Language :: Python :: 3.9
Classifier: Programming Language :: Python :: 3.10
Classifier: Programming Language :: Python :: 3.11
Classifier: Topic :: Scientific/Engineering :: Mathematics
Classifier: Topic :: Software Development :: Libraries :: Python Modules
Requires-Python: >=3.7
Provides-Extra: dev
Requires-Dist: pytest (>=6.0) ; extra == 'dev'
Requires-Dist: pytest-cov (>=2.0) ; extra == 'dev'
Requires-Dist: black (>=21.0) ; extra == 'dev'
Requires-Dist: flake8 (>=3.8) ; extra == 'dev'
Requires-Dist: mypy (>=0.800) ; extra == 'dev'
